Workbook
Name Slicer_Clean_Enrollment_Date: #N/A
Name Slicer_Enrollment_Date: #N/A
Name Slicer_Enrollment_Date1: #N/A
Name Slicer_Enrollment_Status: #N/A
Name Slicer_Enrollment_Status2: #N/A
Name Slicer_Gender: #N/A
Name Slicer_Gender2: #N/A
Name Slicer_Program2: #N/A
Name Slicer_Program4: #N/A
Name Slicer_Study_Mode1: #N/A
Name Slicer_Study_Mode2: #N/A

Sheet Project_Index
A1: No. | B1: Student Name | C1: Project Title | D1: Dataset Sheet | E1: Rows | F1: Columns | G1: Status | I1: Data Quality Note
A2: 1 | B2: Aba Muxudiin Ahmed | C2: Student Enrollment Data Analysis Using Excel | D2: 01_Enrollment | E2: 300 | F2: 7 | G2: Ready | I2: Each project dataset now includes 15 additional empty cells in every one of its 7 columns for missing-value cleaning practice.
A3: 2 | B3: Abdikarim Ismail Ali | C3: Customer Purchase & Sales Performance Analysis Using Excel | D3: 02_Sales | E3: 300 | F3: 7 | G3: Ready
A4: 3 | B4: Abdinajib Abdullahi Muse | C4: Employee Attendance Data Analysis Using Excel | D4: 03_Emp_Attendance | E4: 300 | F4: 7 | G4: Ready
A5: 4 | B5: Aisha Mohamed Abdullahi | C5: Restaurant Sales and Customer Analysis Using Excel | D5: 04_Restaurant | E5: 300 | F5: 7 | G5: Ready
A6: 5 | B6: Aniso Ahmed Mohamud | C6: TITLE NOT PROVIDED | E6: 0 | F6: 0 | G6: Project title needed
A7: 6 | B7: Axmed Abduqadir Iman | C7: Electricity Consumption Data Analysis Using Excel | D7: 06_Electricity | E7: 300 | F7: 7 | G7: Ready
A8: 7 | B8: Ayuub Abdullahi Isxaakh | C8: Hospital Patient Data Analysis Using Excel | D8: 07_Hospital | E8: 300 | F8: 7 | G8: Ready
A9: 8 | B9: Cayni Abuukar Maxamuud | C9: Real Estate Property Data Analysis Using Excel | D9: 08_Real_Estate | E9: 300 | F9: 7 | G9: Ready
A10: 9 | B10: Deqo Abdulkhadir Hussein | C10: Student Attendance and Academic Analysis | D10: 09_Academic | E10: 300 | F10: 7 | G10: Ready
A11: 10 | B11: Faadumo Mahamed Yusuf | C11: Internet Usage Data Analysis | D11: 10_Internet | E11: 300 | F11: 7 | G11: Ready
A12: 11 | B12: Fardowso Gamadiid Imaan | C12: Employee Salary Data Analysis Using Excel | D12: 11_Salary | E12: 300 | F12: 7 | G12: Ready
A13: 12 | B13: Fartun Ali Maxamuud | C13: Fuel Consumption and Vehicle Analysis Using Excel | D13: 12_Fuel | E13: 300 | F13: 7 | G13: Ready
A14: 13 | B14: Faysal Mohamed Dahir | C14: Customer Demographic Data Analysis | D14: 13_Demographic | E14: 300 | F14: 7 | G14: Ready
A15: 14 | B15: Hawo Abdi Maxamed | C15: Weather and Temperature Data Analysis | D15: 14_Weather | E15: 300 | F15: 7 | G15: Ready
A16: 15 | B16: Hudeifa Mohamud Ahmed | C16: Monthly Expense and Budget Analysis | D16: 15_Budget | E16: 300 | F16: 7 | G16: Ready
A17: 16 | B17: Ibrahim Abdullahi Farhan | C17: Public Transportation Performance Analysis | D17: 16_Transport | E17: 300 | F17: 7 | G17: Ready
A18: 17 | B18: Miski Mohamed Abdullahi | C18: Hotel Booking and Customer Analysis | D18: 17_Hotel | E18: 300 | F18: 7 | G18: Ready
... A25: 24 | B25: Sucdi Yasin Husein | C25: Job Recruitment and Applicant Data Analysis | D25: 24_Recruitment | E25: 300 | F25: 7 | G25: Ready

Sheet Dashboard
B8: STUDENT ENROLLMENT DASHBOARD
B12: =COUNTA(#REF!) -> 1 | E12: =COUNTIF(#REF!,"Active") -> #REF! | I12: =COUNTIF(#REF!,"Graduated") -> #REF! | L12: =COUNTIF(#REF!,"Withdrawn") -> #REF!
B14: Total Students | E14: Active Students | I14: Graduated Students | L14: Withdrawn Students
B17: =SUM(#REF!) -> #REF! | I17: =AVERAGE(#REF!) -> #REF!
B20: Total Tuition Fee | I20: Average Tuition Fee

Sheet PivotGender
A3: Row Labels | B3: Count of Student_ID
A4: Female | B4: 148
A5: Male | B5: 136
A6: non_gender | B6: 16
A7: Grand Total | B7: 300

Sheet PivotProgram
A3: Row Labels | B3: Count of Student_ID
A4: Business Administration | B4: 47
A5: Computer Science | B5: 74
A6: Data Science | B6: 65
A7: Economics | B7: 25
A8: Engineering | B8: 37
A9: non_program | B9: 17
A10: Public Health | B10: 35
A11: Grand Total | B11: 300

Sheet PivotEnrollment_status
A3: Row Labels | B3: Count of Student_ID
A4: Active | B4: 175
A5: Deferred | B5: 27
A6: Graduated | B6: 64
A7: non_status | B7: 18
A8: Withdrawn | B8: 16
A9: Grand Total | B9: 300

Sheet PivotTuitionByProgram
A3: Row Labels | B3: Sum of Tuition_Fee
A4: Business Administration | B4: 36617.5
A5: Computer Science | B5: 68526.92
A6: Data Science | B6: 65662.73
A7: Economics | B7: 19402.25
A8: Engineering | B8: 42936.93
A9: non_program | B9: 17318.41
A10: Public Health | B10: 30457.95
A11: Grand Total | B11: 280922.69

Sheet PivotStady_mode
A3: Row Labels | B3: Count of Student_ID
A4: Full-Time | B4: 162
A5: non_stady_mode | B5: 19
A6: Online | B6: 60
A7: Part-Time | B7: 59
A8: Grand Total | B8: 300

Sheet PivotEnrollment_date
A3: Row Labels | B3: Count of Student_ID
A4: #VALUE! | B4: 18
A5: 1 | B5: 26
A6: 11 | B6: 23
A7: 12 | B7: 34
A8: 2 | B8: 20
A9: 3 | B9: 6
A10: 5 | B10: 10
A11: 6 | B11: 55
A12: 7 | B12: 78
A13: 8 | B13: 30
A14: Grand Total | B14: 300

Sheet PivotErollment_status
A3: Row Labels | B3: Count of Tuition_Fee
A4: Active | B4: 175
A5: Deferred | B5: 27
A6: Graduated | B6: 64
A7: non_status | B7: 18
A8: Withdrawn | B8: 16
A9: Grand Total | B9: 300

Sheet Sheet22
A3: Row Labels | B3: Sum of Tuition_Fee
A4: 45658 | B4: 772.18
A5: 45662 | B5: 1018
A6: 45663 | B6: 2298.6
A7: 45667 | B7: 1165.03
A8: 45668 | B8: 0
A9: 45669 | B9: 922.81
A10: 45672 | B10: 1087.06
A11: 45673 | B11: 984.71
A12: 45675 | B12: 1817.78
A13: 45678 | B13: 1022.73
A14: 45679 | B14: 858.41
A15: 45682 | B15: 1014.93
... A220: 46221 | B220: 1140.65
A221: Grand Total | B221: 262962.74

Sheet PivotTuitionByStudy_mode
A3: Row Labels | B3: Average of Tuition_Fee
A4: Active | B4: 973.18382
A5: Deferred | B5: 1057.798
A6: Graduated | B6: 1022.0213
A7: non_status | B7: 1003.02
A8: Withdrawn | B8: 1037.6264
A9: Grand Total | B9: 996.17975

Sheet Sheet29
A3: Row Labels | B3: Count of Tuition_Fee
A4: 1 | B4: 26
A5: 11 | B5: 23
A6: 12 | B6: 34
A7: 2 | B7: 20
A8: 3 | B8: 6
A9: 5 | B9: 10
A10: 6 | B10: 55
A11: 7 | B11: 78
A12: 8 | B12: 30
A13: Grand Total | B13: 282

Sheet DASHBOARD2
D6: DASHBOARD ENROLLMENT
D10: =GETPIVOTDATA("Student_ID",PivotGender!$A$3) -> 300 | G10: =GETPIVOTDATA("Tuition_Fee",PivotErollment_status!$A$3,"Enrollment_Status","Active") -> 175 | J10: =GETPIVOTDATA("Tuition_Fee",PivotErollment_status!$A$3,"Enrollment_Status","Graduated") -> 64 | M10: =GETPIVOTDATA("Tuition_Fee",PivotTuitionByStudy_mode!$A$3) -> 996.17975 | P10: =GETPIVOTDATA("Tuition_Fee",Avaregetuition!$A$3) -> 996.17975
D13: TOTAL STUDENT | G13: ACTIVE | J13: GRADUATED | M13: TOTAL TUITION | P13: AVG TUITION

Sheet Sheet31
A3: Row Labels | B3: Count of Tuition_Fee
A4: Full-Time | B4: 162
A5: non_stady_mode | B5: 19
A6: Online | B6: 60
A7: Part-Time | B7: 59
A8: Grand Total | B8: 300

Sheet Study_mode
A3: Row Labels | B3: Count of Student_ID
A4: Full-Time | B4: 162
A5: non_stady_mode | B5: 19
A6: Online | B6: 60
A7: Part-Time | B7: 59
A8: Grand Total | B8: 300

Sheet Avaregetuition
A3: Average of Tuition_Fee
A4: 996.17975

Sheet Data_clean
A1: Student_ID | B1: Gender | C1: Program | D1: Enrollment_Date | E1: Study_Mode | F1: Tuition_Fee | G1: Enrollment_Status | H1: Year | I1: Monthly | J1: Clean_Enrollment_Date
A2: ENR0001 | B2: Male | C2: Computer Science | D2: 45994 | E2: Full-Time | F2: 927.99 | G2: non_status | H2: =YEAR(Table1[[#This Row],[Enrollment_Date]]) -> 2025 | I2: =MONTH(Table1[[#This Row],[Enrollment_Date]]) -> 12 | J2: =IF(ISNUMBER(D2),D2,"") -> 45994
A3: ENR0002 | B3: Female | C3: Computer Science | D3: 45995 | E3: Online | F3: 929.8 | G3: Active | H3: =YEAR(Table1[[#This Row],[Enrollment_Date]]) -> 2025 | I3: =MONTH(Table1[[#This Row],[Enrollment_Date]]) -> 12 | J3: =IF(ISNUMBER(D3),D3,"") -> 45995
A4: ENR0003 | B4: Male | C4: Public Health | D4: 45996 | E4: Full-Time | F4: 1028.35 | G4: Active | H4: =YEAR(Table1[[#This Row],[Enrollment_Date]]) -> 2025 | I4: =MONTH(Table1[[#This Row],[Enrollment_Date]]) -> 12 | J4: =IF(ISNUMBER(D4),D4,"") -> 45996
A5: ENR0004 | B5: Male | C5: Data Science | D5: 45997 | E5: Part-Time | F5: 0 | G5: Active | H5: =YEAR(Table1[[#This Row],[Enrollment_Date]]) -> 2025 | I5: =MONTH(Table1[[#This Row],[Enrollment_Date]]) -> 12 | J5: =IF(ISNUMBER(D5),D5,"") -> 45997
A6: ENR0005 | B6: Female | C6: Computer Science | D6: 45998 | E6: Full-Time | F6: 1035.39 | G6: Active | H6: =YEAR(Table1[[#This Row],[Enrollment_Date]]) -> 2025 | I6: =MONTH(Table1[[#This Row],[Enrollment_Date]]) -> 12 | J6: =IF(ISNUMBER(D6),D6,"") -> 45998
A7: ENR0006 | B7: Female | C7: non_program | D7: 45999 | E7: Full-Time | F7: 1254.82 | G7: Withdrawn | H7: =YEAR(Table1[[#This Row],[Enrollment_Date]]) -> 2025 | I7: =MONTH(Table1[[#This Row],[Enrollment_Date]]) -> 12 | J7: =IF(ISNUMBER(D7),D7,"") -> 45999
A8: ENR0007 | B8: Male | C8: Public Health | D8: 46000 | E8: Full-Time | F8: 825.79 | G8: Graduated | H8: =YEAR(Table1[[#This Row],[Enrollment_Date]]) -> 2025 | I8: =MONTH(Table1[[#This Row],[Enrollment_Date]]) -> 12 | J8: =IF(ISNUMBER(D8),D8,"") -> 46000
A9: ENR0008 | B9: Male | C9: Computer Science | D9: 46001 | E9: Part-Time | F9: 1034.99 | G9: Deferred | H9: =YEAR(Table1[[#This Row],[Enrollment_Date]]) -> 2025 | I9: =MONTH(Table1[[#This Row],[Enrollment_Date]]) -> 12 | J9: =IF(ISNUMBER(D9),D9,"") -> 46001
A10: ENR0009 | B10: Female | C10: Computer Science | D10: 46002 | E10: Full-Time | F10: 1006.87 | G10: Active | H10: =YEAR(Table1[[#This Row],[Enrollment_Date]]) -> 2025 | I10: =MONTH(Table1[[#This Row],[Enrollment_Date]]) -> 12 | J10: =IF(ISNUMBER(D10),D10,"") -> 46002
A11: ENR0010 | B11: non_gender | C11: Computer Science | D11: 46003 | E11: Part-Time | F11: 896.69 | G11: Graduated | H11: =YEAR(Table1[[#This Row],[Enrollment_Date]]) -> 2025 | I11: =MONTH(Table1[[#This Row],[Enrollment_Date]]) -> 12 | J11: =IF(ISNUMBER(D11),D11,"") -> 46003
A12: ENR0011 | B12: Female | C12: Computer Science | D12: 46004 | E12: Part-Time | F12: 1046.24 | G12: Graduated | H12: =YEAR(Table1[[#This Row],[Enrollment_Date]]) -> 2025 | I12: =MONTH(Table1[[#This Row],[Enrollment_Date]]) -> 12 | J12: =IF(ISNUMBER(D12),D12,"") -> 46004
A13: ENR0012 | B13: Male | C13: Data Science | D13: 46005 | E13: non_stady_mode | F13: 0 | G13: Active | H13: =YEAR(Table1[[#This Row],[Enrollment_Date]]) -> 2025 | I13: =MONTH(Table1[[#This Row],[Enrollment_Date]]) -> 12 | J13: =IF(ISNUMBER(D13),D13,"") -> 46005
... A23: ENR0022 | B23: Female | C23: Public Health | D23: 46015 | E23: Full-Time | F23: 0 | G23: Withdrawn | H23: =YEAR(Table1[[#This Row],[Enrollment_Date]]) -> 2025 | I23: =MONTH(Table1[[#This Row],[Enrollment_Date]]) -> 12 | J23: =IF(ISNUMBER(D23),D23,"") -> 46015
A24: ENR0023 | B24: Female | C24: Data Science | D24: non_date | E24: Full-Time | F24: 1129.42 | G24: Graduated | H24: =YEAR(Table1[[#This Row],[Enrollment_Date]]) -> #VALUE! | I24: =MONTH(Table1[[#This Row],[Enrollment_Date]]) -> #VALUE! | J24: =IF(ISNUMBER(D24),D24,"")
A25: ENR0024 | B25: Female | C25: Data Science | D25: non_date | E25: Full-Time | F25: 1048 | G25: Active | H25: =YEAR(Table1[[#This Row],[Enrollment_Date]]) -> #VALUE! | I25: =MONTH(Table1[[#This Row],[Enrollment_Date]]) -> #VALUE! | J25: =IF(ISNUMBER(D25),D25,"")
A26: ENR0025 | B26: Female | C26: Data Science | D26: 45887 | E26: Full-Time | F26: 0 | G26: Active | H26: =YEAR(Table1[[#This Row],[Enrollment_Date]]) -> 2025 | I26: =MONTH(Table1[[#This Row],[Enrollment_Date]]) -> 8 | J26: =IF(ISNUMBER(D26),D26,"") -> 45887
A27: ENR0026 | B27: Male | C27: Computer Science | D27: 45888 | E27: non_stady_mode | F27: 1014.33 | G27: Graduated | H27: =YEAR(Table1[[#This Row],[Enrollment_Date]]) -> 2025 | I27: =MONTH(Table1[[#This Row],[Enrollment_Date]]) -> 8 | J27: =IF(ISNUMBER(D27),D27,"") -> 45888
A28: ENR0027 | B28: Male | C28: Public Health | D28: 45889 | E28: Full-Time | F28: 877.02 | G28: Active | H28: =YEAR(Table1[[#This Row],[Enrollment_Date]]) -> 2025 | I28: =MONTH(Table1[[#This Row],[Enrollment_Date]]) -> 8 | J28: =IF(ISNUMBER(D28),D28,"") -> 45889
A29: ENR0028 | B29: Female | C29: Data Science | D29: 45890 | E29: Full-Time | F29: 0 | G29: Active | H29: =YEAR(Table1[[#This Row],[Enrollment_Date]]) -> 2025 | I29: =MONTH(Table1[[#This Row],[Enrollment_Date]]) -> 8 | J29: =IF(ISNUMBER(D29),D29,"") -> 45890
A30: ENR0029 | B30: Male | C30: Public Health | D30: 45891 | E30: Full-Time | F30: 922.81 | G30: Active | H30: =YEAR(Table1[[#This Row],[Enrollment_Date]]) -> 2025 | I30: =MONTH(Table1[[#This Row],[Enrollment_Date]]) -> 8 | J30: =IF(ISNUMBER(D30),D30,"") -> 45891
A31: ENR0030 | B31: Male | C31: Data Science | D31: 45892 | E31: Full-Time | F31: 1155.26 | G31: Graduated | H31: =YEAR(Table1[[#This Row],[Enrollment_Date]]) -> 2025 | I31: =MONTH(Table1[[#This Row],[Enrollment_Date]]) -> 8 | J31: =IF(ISNUMBER(D31),D31,"") -> 45892
A32: ENR0031 | B32: Female | C32: Computer Science | D32: 45893 | E32: Full-Time | F32: 1064.99 | G32: Active | H32: =YEAR(Table1[[#This Row],[Enrollment_Date]]) -> 2025 | I32: =MONTH(Table1[[#This Row],[Enrollment_Date]]) -> 8 | J32: =IF(ISNUMBER(D32),D32,"") -> 45893
A33: ENR0032 | B33: Female | C33: Business Administration | D33: non_date | E33: non_stady_mode | F33: 808.66 | G33: Active | H33: =YEAR(Table1[[#This Row],[Enrollment_Date]]) -> #VALUE! | I33: =MONTH(Table1[[#This Row],[Enrollment_Date]]) -> #VALUE! | J33: =IF(ISNUMBER(D33),D33,"")
A34: ENR0033 | B34: Female | C34: Business Administration | D34: 46066 | E34: Part-Time | F34: 834.99 | G34: Active | H34: =YEAR(Table1[[#This Row],[Enrollment_Date]]) -> 2026 | I34: =MONTH(Table1[[#This Row],[Enrollment_Date]]) -> 2 | J34: =IF(ISNUMBER(D34),D34,"") -> 46066
A35: ENR0034 | B35: Male | C35: Public Health | D35: 46067 | E35: Full-Time | F35: 972.65 | G35: non_status | H35: =YEAR(Table1[[#This Row],[Enrollment_Date]]) -> 2026 | I35: =MONTH(Table1[[#This Row],[Enrollment_Date]]) -> 2 | J35: =IF(ISNUMBER(D35),D35,"") -> 46067
A36: ENR0035 | B36: Male | C36: Computer Science | D36: 46068 | E36: Online | F36: 886.2 | G36: non_status | H36: =YEAR(Table1[[#This Row],[Enrollment_Date]]) -> 2026 | I36: =MONTH(Table1[[#This Row],[Enrollment_Date]]) -> 2 | J36: =IF(ISNUMBER(D36),D36,"") -> 46068
A37: ENR0036 | B37: Female | C37: Business Administration | D37: 46069 | E37: non_stady_mode | F37: 866.74 | G37: non_status | H37: =YEAR(Table1[[#This Row],[Enrollment_Date]]) -> 2026 | I37: =MONTH(Table1[[#This Row],[Enrollment_Date]]) -> 2 | J37: =IF(ISNUMBER(D37),D37,"") -> 46069
A38: ENR0037 | B38: Male | C38: Data Science | D38: 46070 | E38: Full-Time | F38: 0 | G38: Active | H38: =YEAR(Table1[[#This Row],[Enrollment_Date]]) -> 2026 | I38: =MONTH(Table1[[#This Row],[Enrollment_Date]]) -> 2 | J38: =IF(ISNUMBER(D38),D38,"") -> 46070
A39: ENR0038 | B39: Female | C39: Business Administration | D39: 46071 | E39: Online | F39: 750.89 | G39: Active | H39: =YEAR(Table1[[#This Row],[Enrollment_Date]]) -> 2026 | I39: =MONTH(Table1[[#This Row],[Enrollment_Date]]) -> 2 | J39: =IF(ISNUMBER(D39),D39,"") -> 46071
A40: ENR0039 | B40: Male | C40: Business Administration | D40: 46072 | E40: Full-Time | F40: 736.59 | G40: Active | H40: =YEAR(Table1[[#This Row],[Enrollment_Date]]) -> 2026 | I40: =MONTH(Table1[[#This Row],[Enrollment_Date]]) -> 2 | J40: =IF(ISNUMBER(D40),D40,"") -> 46072
A41: ENR0040 | B41: Female | C41: Computer Science | D41: 46073 | E41: Full-Time | F41: 1071.49 | G41: Graduated | H41: =YEAR(Table1[[#This Row],[Enrollment_Date]]) -> 2026 | I41: =MONTH(Table1[[#This Row],[Enrollment_Date]]) -> 2 | J41: =IF(ISNUMBER(D41),D41,"") -> 46073
A42: ENR0041 | B42: Male | C42: Business Administration | D42: non_date | E42: Part-Time | F42: 838.79 | G42: Active | H42: =YEAR(Table1[[#This Row],[Enrollment_Date]]) -> #VALUE! | I42: =MONTH(Table1[[#This Row],[Enrollment_Date]]) -> #VALUE! | J42: =IF(ISNUMBER(D42),D42,"")
A43: ENR0042 | B43: non_gender | C43: Public Health | D43: 46213 | E43: Online | F43: 960.91 | G43: Active | H43: =YEAR(Table1[[#This Row],[Enrollment_Date]]) -> 2026 | I43: =MONTH(Table1[[#This Row],[Enrollment_Date]]) -> 7 | J43: =IF(ISNUMBER(D43),D43,"") -> 46213
A44: ENR0043 | B44: Male | C44: Engineering | D44: 46214 | E44: Part-Time | F44: 1354.04 | G44: Deferred | H44: =YEAR(Table1[[#This Row],[Enrollment_Date]]) -> 2026 | I44: =MONTH(Table1[[#This Row],[Enrollment_Date]]) -> 7 | J44: =IF(ISNUMBER(D44),D44,"") -> 46214
A45: ENR0044 | B45: Male | C45: Business Administration | D45: 46215 | E45: Full-Time | F45: 789.47 | G45: Deferred | H45: =YEAR(Table1[[#This Row],[Enrollment_Date]]) -> 2026 | I45: =MONTH(Table1[[#This Row],[Enrollment_Date]]) -> 7 | J45: =IF(ISNUMBER(D45),D45,"") -> 46215
A46: ENR0045 | B46: Female | C46: Engineering | D46: 46216 | E46: Online | F46: 1208.64 | G46: non_status | H46: =YEAR(Table1[[#This Row],[Enrollment_Date]]) -> 2026 | I46: =MONTH(Table1[[#This Row],[Enrollment_Date]]) -> 7 | J46: =IF(ISNUMBER(D46),D46,"") -> 46216
A47: ENR0046 | B47: Female | C47: Business Administration | D47: 46217 | E47: Full-Time | F47: 792.99 | G47: Active | H47: =YEAR(Table1[[#This Row],[Enrollment_Date]]) -> 2026 | I47: =MONTH(Table1[[#This Row],[Enrollment_Date]]) -> 7 | J47: =IF(ISNUMBER(D47),D47,"") -> 46217
A48: ENR0047 | B48: Female | C48: Data Science | D48: 46218 | E48: Online | F48: 1084.15 | G48: Graduated | H48: =YEAR(Table1[[#This Row],[Enrollment_Date]]) -> 2026 | I48: =MONTH(Table1[[#This Row],[Enrollment_Date]]) -> 7 | J48: =IF(ISNUMBER(D48),D48,"") -> 46218
A49: ENR0048 | B49: Female | C49: Engineering | D49: 46219 | E49: Full-Time | F49: 1305.94 | G49: Graduated | H49: =YEAR(Table1[[#This Row],[Enrollment_Date]]) -> 2026 | I49: =MONTH(Table1[[#This Row],[Enrollment_Date]]) -> 7 | J49: =IF(ISNUMBER(D49),D49,"") -> 46219
A50: ENR0049 | B50: Female | C50: Public Health | D50: 46220 | E50: Full-Time | F50: 0 | G50: Graduated | H50: =YEAR(Table1[[#This Row],[Enrollment_Date]]) -> 2026 | I50: =MONTH(Table1[[#This Row],[Enrollment_Date]]) -> 7 | J50: =IF(ISNUMBER(D50),D50,"") -> 46220
A51: ENR0050 | B51: Male | C51: Public Health | D51: non_date | E51: Part-Time | F51: 1000.77 | G51: Active | H51: =YEAR(Table1[[#This Row],[Enrollment_Date]]) -> #VALUE! | I51: =MONTH(Table1[[#This Row],[Enrollment_Date]]) -> #VALUE! | J51: =IF(ISNUMBER(D51),D51,"")
A52: ENR0051 | B52: Male | C52: Computer Science | D52: 45983 | E52: Full-Time | F52: 928.88 | G52: Active | H52: =YEAR(Table1[[#This Row],[Enrollment_Date]]) -> 2025 | I52: =MONTH(Table1[[#This Row],[Enrollment_Date]]) -> 11 | J52: =IF(ISNUMBER(D52),D52,"") -> 45983
A53: ENR0052 | B53: Male | C53: Computer Science | D53: 45984 | E53: Full-Time | F53: 928.88 | G53: Active | H53: =YEAR(Table1[[#This Row],[Enrollment_Date]]) -> 2025 | I53: =MONTH(Table1[[#This Row],[Enrollment_Date]]) -> 11 | J53: =IF(ISNUMBER(D53),D53,"") -> 45984
A54: ENR0053 | B54: Female | C54: Data Science | D54: 45985 | E54: Full-Time | F54: 0 | G54: Graduated | H54: =YEAR(Table1[[#This Row],[Enrollment_Date]]) -> 2025 | I54: =MONTH(Table1[[#This Row],[Enrollment_Date]]) -> 11 | J54: =IF(ISNUMBER(D54),D54,"") -> 45985
A55: ENR0054 | B55: Male | C55: Engineering | D55: 45986 | E55: Full-Time | F55: 1142.6 | G55: Active | H55: =YEAR(Table1[[#This Row],[Enrollment_Date]]) -> 2025 | I55: =MONTH(Table1[[#This Row],[Enrollment_Date]]) -> 11 | J55: =IF(ISNUMBER(D55),D55,"") -> 45986
A56: ENR0055 | B56: Male | C56: Computer Science | D56: 45987 | E56: Full-Time | F56: 1042.66 | G56: Graduated | H56: =YEAR(Table1[[#This Row],[Enrollment_Date]]) -> 2025 | I56: =MONTH(Table1[[#This Row],[Enrollment_Date]]) -> 11 | J56: =IF(ISNUMBER(D56),D56,"") -> 45987
A57: ENR0056 | B57: Male | C57: Data Science | D57: 45988 | E57: Full-Time | F57: 1252.22 | G57: Deferred | H57: =YEAR(Table1[[#This Row],[Enrollment_Date]]) -> 2025 | I57: =MONTH(Table1[[#This Row],[Enrollment_Date]]) -> 11 | J57: =IF(ISNUMBER(D57),D57,"") -> 45988
A58: ENR0057 | B58: Male | C58: Engineering | D58: non_date | E58: Full-Time | F58: 1116.57 | G58: Active | H58: =YEAR(Table1[[#This Row],[Enrollment_Date]]) -> #VALUE! | I58: =MONTH(Table1[[#This Row],[Enrollment_Date]]) -> #VALUE! | J58: =IF(ISNUMBER(D58),D58,"")
A59: ENR0058 | B59: Female | C59: Engineering | D59: 45817 | E59: Part-Time | F59: 1120 | G59: Active | H59: =YEAR(Table1[[#This Row],[Enrollment_Date]]) -> 2025 | I59: =MONTH(Table1[[#This Row],[Enrollment_Date]]) -> 6 | J59: =IF(ISNUMBER(D59),D59,"") -> 45817
A60: ENR0059 | B60: Male | C60: Data Science | D60: 45818 | E60: Full-Time | F60: 1187.61 | G60: Active | H60: =YEAR(Table1[[#This Row],[Enrollment_Date]]) -> 2025 | I60: =MONTH(Table1[[#This Row],[Enrollment_Date]]) -> 6 | J60: =IF(ISNUMBER(D60),D60,"") -> 45818
A61: ENR0060 | B61: Female | C61: Economics | D61: 45819 | E61: Part-Time | F61: 874.8 | G61: Active | H61: =YEAR(Table1[[#This Row],[Enrollment_Date]]) -> 2025 | I61: =MONTH(Table1[[#This Row],[Enrollment_Date]]) -> 6 | J61: =IF(ISNUMBER(D61),D61,"") -> 45819
A62: ENR0061 | B62: Female | C62: Economics | D62: 45820 | E62: Part-Time | F62: 874.8 | G62: Active | H62: =YEAR(Table1[[#This Row],[Enrollment_Date]]) -> 2025 | I62: =MONTH(Table1[[#This Row],[Enrollment_Date]]) -> 6 | J62: =IF(ISNUMBER(D62),D62,"") -> 45820
A63: ENR0062 | B63: Female | C63: Public Health | D63: 45821 | E63: Full-Time | F63: 816.32 | G63: Graduated | H63: =YEAR(Table1[[#This Row],[Enrollment_Date]]) -> 2025 | I63: =MONTH(Table1[[#This Row],[Enrollment_Date]]) -> 6 | J63: =IF(ISNUMBER(D63),D63,"") -> 45821
A64: ENR0063 | B64: Female | C64: Public Health | D64: 45822 | E64: Full-Time | F64: 944.77 | G64: Graduated | H64: =YEAR(Table1[[#This Row],[Enrollment_Date]]) -> 2025 | I64: =MONTH(Table1[[#This Row],[Enrollment_Date]]) -> 6 | J64: =IF(ISNUMBER(D64),D64,"") -> 45822
A65: ENR0064 | B65: Male | C65: Engineering | D65: 45823 | E65: non_stady_mode | F65: 1155.73 | G65: Active | H65: =YEAR(Table1[[#This Row],[Enrollment_Date]]) -> 2025 | I65: =MONTH(Table1[[#This Row],[Enrollment_Date]]) -> 6 | J65: =IF(ISNUMBER(D65),D65,"") -> 45823
A66: ENR0065 | B66: Female | C66: Computer Science | D66: 45824 | E66: Online | F66: 1014.93 | G66: Graduated | H66: =YEAR(Table1[[#This Row],[Enrollment_Date]]) -> 2025 | I66: =MONTH(Table1[[#This Row],[Enrollment_Date]]) -> 6 | J66: =IF(ISNUMBER(D66),D66,"") -> 45824
A67: ENR0066 | B67: Female | C67: Data Science | D67: 45825 | E67: Full-Time | F67: 1186.5 | G67: Deferred | H67: =YEAR(Table1[[#This Row],[Enrollment_Date]]) -> 2025 | I67: =MONTH(Table1[[#This Row],[Enrollment_Date]]) -> 6 | J67: =IF(ISNUMBER(D67),D67,"") -> 45825
A68: ENR0067 | B68: Male | C68: Business Administration | D68: 45826 | E68: Full-Time | F68: 887.69 | G68: Withdrawn | H68: =YEAR(Table1[[#This Row],[Enrollment_Date]]) -> 2025 | I68: =MONTH(Table1[[#This Row],[Enrollment_Date]]) -> 6 | J68: =IF(ISNUMBER(D68),D68,"") -> 45826
A69: ENR0068 | B69: Female | C69: Engineering | D69: 45827 | E69: Full-Time | F69: 1164.86 | G69: Withdrawn | H69: =YEAR(Table1[[#This Row],[Enrollment_Date]]) -> 2025 | I69: =MONTH(Table1[[#This Row],[Enrollment_Date]]) -> 6 | J69: =IF(ISNUMBER(D69),D69,"") -> 45827
A70: ENR0069 | B70: non_gender | C70: Business Administration | D70: 45828 | E70: Part-Time | F70: 865.04 | G70: Active | H70: =YEAR(Table1[[#This Row],[Enrollment_Date]]) -> 2025 | I70: =MONTH(Table1[[#This Row],[Enrollment_Date]]) -> 6 | J70: =IF(ISNUMBER(D70),D70,"") -> 45828
... A104: ENR0103 | B104: Female | C104: Data Science | D104: 45862 | E104: Full-Time | F104: 1173.08 | G104: Deferred | H104: =YEAR(Table1[[#This Row],[Enrollment_Date]]) -> 2025 | I104: =MONTH(Table1[[#This Row],[Enrollment_Date]]) -> 7 | J104: =IF(ISNUMBER(D104),D104,"") -> 45862
A105: ENR0104 | B105: Male | C105: Data Science | D105: non_date | E105: Online | F105: 1105.23 | G105: Graduated | H105: =YEAR(Table1[[#This Row],[Enrollment_Date]]) -> #VALUE! | I105: =MONTH(Table1[[#This Row],[Enrollment_Date]]) -> #VALUE! | J105: =IF(ISNUMBER(D105),D105,"")
A106: ENR0105 | B106: Male | C106: Economics | D106: 45869 | E106: Full-Time | F106: 866.46 | G106: Active | H106: =YEAR(Table1[[#This Row],[Enrollment_Date]]) -> 2025 | I106: =MONTH(Table1[[#This Row],[Enrollment_Date]]) -> 7 | J106: =IF(ISNUMBER(D106),D106,"") -> 45869
A107: ENR0106 | B107: Male | C107: Public Health | D107: 45870 | E107: Online | F107: 857.18 | G107: Graduated | H107: =YEAR(Table1[[#This Row],[Enrollment_Date]]) -> 2025 | I107: =MONTH(Table1[[#This Row],[Enrollment_Date]]) -> 8 | J107: =IF(ISNUMBER(D107),D107,"") -> 45870
A108: ENR0107 | B108: Female | C108: Public Health | D108: 45871 | E108: Full-Time | F108: 815.31 | G108: Active | H108: =YEAR(Table1[[#This Row],[Enrollment_Date]]) -> 2025 | I108: =MONTH(Table1[[#This Row],[Enrollment_Date]]) -> 8 | J108: =IF(ISNUMBER(D108),D108,"") -> 45871
A109: ENR0108 | B109: Female | C109: Economics | D109: 45872 | E109: Full-Time | F109: 832.04 | G109: Active | H109: =YEAR(Table1[[#This Row],[Enrollment_Date]]) -> 2025 | I109: =MONTH(Table1[[#This Row],[Enrollment_Date]]) -> 8 | J109: =IF(ISNUMBER(D109),D109,"") -> 45872
A110: ENR0109 | B110: Female | C110: Data Science | D110: 45873 | E110: Full-Time | F110: 1235.12 | G110: Active | H110: =YEAR(Table1[[#This Row],[Enrollment_Date]]) -> 2025 | I110: =MONTH(Table1[[#This Row],[Enrollment_Date]]) -> 8 | J110: =IF(ISNUMBER(D110),D110,"") -> 45873
A111: ENR0110 | B111: Male | C111: Computer Science | D111: 45874 | E111: Online | F111: 969.17 | G111: Graduated | H111: =YEAR(Table1[[#This Row],[Enrollment_Date]]) -> 2025 | I111: =MONTH(Table1[[#This Row],[Enrollment_Date]]) -> 8 | J111: =IF(ISNUMBER(D111),D111,"") -> 45874
A112: ENR0111 | B112: non_gender | C112: Data Science | D112: 45875 | E112: Full-Time | F112: 1021.44 | G112: Active | H112: =YEAR(Table1[[#This Row],[Enrollment_Date]]) -> 2025 | I112: =MONTH(Table1[[#This Row],[Enrollment_Date]]) -> 8 | J112: =IF(ISNUMBER(D112),D112,"") -> 45875
A113: ENR0112 | B113: Male | C113: Public Health | D113: 45876 | E113: Part-Time | F113: 954.23 | G113: Active | H113: =YEAR(Table1[[#This Row],[Enrollment_Date]]) -> 2025 | I113: =MONTH(Table1[[#This Row],[Enrollment_Date]]) -> 8 | J113: =IF(ISNUMBER(D113),D113,"") -> 45876
A114: ENR0113 | B114: Female | C114: Computer Science | D114: 45877 | E114: Online | F114: 998.74 | G114: Active | H114: =YEAR(Table1[[#This Row],[Enrollment_Date]]) -> 2025 | I114: =MONTH(Table1[[#This Row],[Enrollment_Date]]) -> 8 | J114: =IF(ISNUMBER(D114),D114,"") -> 45877
A115: ENR0114 | B115: Male | C115: Engineering | D115: 45878 | E115: Online | F115: 1246.84 | G115: Deferred | H115: =YEAR(Table1[[#This Row],[Enrollment_Date]]) -> 2025 | I115: =MONTH(Table1[[#This Row],[Enrollment_Date]]) -> 8 | J115: =IF(ISNUMBER(D115),D115,"") -> 45878
A116: ENR0115 | B116: Male | C116: Computer Science | D116: 45879 | E116: Full-Time | F116: 984.71 | G116: Active | H116: =YEAR(Table1[[#This Row],[Enrollment_Date]]) -> 2025 | I116: =MONTH(Table1[[#This Row],[Enrollment_Date]]) -> 8 | J116: =IF(ISNUMBER(D116),D116,"") -> 45879
A117: ENR0116 | B117: Female | C117: Computer Science | D117: 45880 | E117: non_stady_mode | F117: 893.1 | G117: Active | H117: =YEAR(Table1[[#This Row],[Enrollment_Date]]) -> 2025 | I117: =MONTH(Table1[[#This Row],[Enrollment_Date]]) -> 8 | J117: =IF(ISNUMBER(D117),D117,"") -> 45880
... A119: ENR0118 | B119: non_gender | C119: Public Health | D119: 45882 | E119: Part-Time | F119: 913.93 | G119: Active | H119: =YEAR(Table1[[#This Row],[Enrollment_Date]]) -> 2025 | I119: =MONTH(Table1[[#This Row],[Enrollment_Date]]) -> 8 | J119: =IF(ISNUMBER(D119),D119,"") -> 45882
A120: ENR0119 | B120: Male | C120: Business Administration | D120: non_date | E120: Full-Time | F120: 899.84 | G120: Active | H120: =YEAR(Table1[[#This Row],[Enrollment_Date]]) -> #VALUE! | I120: =MONTH(Table1[[#This Row],[Enrollment_Date]]) -> #VALUE! | J120: =IF(ISNUMBER(D120),D120,"")
A121: ENR0120 | B121: Female | C121: Computer Science | D121: 45969 | E121: Full-Time | F121: 1043.3 | G121: Active | H121: =YEAR(Table1[[#This Row],[Enrollment_Date]]) -> 2025 | I121: =MONTH(Table1[[#This Row],[Enrollment_Date]]) -> 11 | J121: =IF(ISNUMBER(D121),D121,"") -> 45969
A122: ENR0121 | B122: Male | C122: Economics | D122: non_date | E122: Online | F122: 717.16 | G122: Active | H122: =YEAR(Table1[[#This Row],[Enrollment_Date]]) -> #VALUE! | I122: =MONTH(Table1[[#This Row],[Enrollment_Date]]) -> #VALUE! | J122: =IF(ISNUMBER(D122),D122,"")
A123: ENR0122 | B123: Female | C123: Computer Science | D123: 46028 | E123: Full-Time | F123: 1037.53 | G123: Graduated | H123: =YEAR(Table1[[#This Row],[Enrollment_Date]]) -> 2026 | I123: =MONTH(Table1[[#This Row],[Enrollment_Date]]) -> 1 | J123: =IF(ISNUMBER(D123),D123,"") -> 46028
A124: ENR0123 | B124: Female | C124: Data Science | D124: 46029 | E124: non_stady_mode | F124: 1260.08 | G124: Withdrawn | H124: =YEAR(Table1[[#This Row],[Enrollment_Date]]) -> 2026 | I124: =MONTH(Table1[[#This Row],[Enrollment_Date]]) -> 1 | J124: =IF(ISNUMBER(D124),D124,"") -> 46029
A125: ENR0124 | B125: Male | C125: Business Administration | D125: 46030 | E125: Part-Time | F125: 808.9 | G125: Active | H125: =YEAR(Table1[[#This Row],[Enrollment_Date]]) -> 2026 | I125: =MONTH(Table1[[#This Row],[Enrollment_Date]]) -> 1 | J125: =IF(ISNUMBER(D125),D125,"") -> 46030
A126: ENR0125 | B126: Female | C126: Data Science | D126: 46031 | E126: Full-Time | F126: 1204.23 | G126: Active | H126: =YEAR(Table1[[#This Row],[Enrollment_Date]]) -> 2026 | I126: =MONTH(Table1[[#This Row],[Enrollment_Date]]) -> 1 | J126: =IF(ISNUMBER(D126),D126,"") -> 46031
A127: ENR0126 | B127: Female | C127: Business Administration | D127: 46032 | E127: Full-Time | F127: 792.94 | G127: Active | H127: =YEAR(Table1[[#This Row],[Enrollment_Date]]) -> 2026 | I127: =MONTH(Table1[[#This Row],[Enrollment_Date]]) -> 1 | J127: =IF(ISNUMBER(D127),D127,"") -> 46032
A128: ENR0127 | B128: Male | C128: Public Health | D128: 46033 | E128: Full-Time | F128: 989.73 | G128: Graduated | H128: =YEAR(Table1[[#This Row],[Enrollment_Date]]) -> 2026 | I128: =MONTH(Table1[[#This Row],[Enrollment_Date]]) -> 1 | J128: =IF(ISNUMBER(D128),D128,"") -> 46033
A129: ENR0128 | B129: Female | C129: Public Health | D129: 46034 | E129: Part-Time | F129: 864.1 | G129: Active | H129: =YEAR(Table1[[#This Row],[Enrollment_Date]]) -> 2026 | I129: =MONTH(Table1[[#This Row],[Enrollment_Date]]) -> 1 | J129: =IF(ISNUMBER(D129),D129,"") -> 46034
A130: ENR0129 | B130: Female | C130: Data Science | D130: 46035 | E130: Full-Time | F130: 1143.52 | G130: Active | H130: =YEAR(Table1[[#This Row],[Enrollment_Date]]) -> 2026 | I130: =MONTH(Table1[[#This Row],[Enrollment_Date]]) -> 1 | J130: =IF(ISNUMBER(D130),D130,"") -> 46035
A131: ENR0130 | B131: Male | C131: Public Health | D131: 46036 | E131: Full-Time | F131: 1006.17 | G131: non_status | H131: =YEAR(Table1[[#This Row],[Enrollment_Date]]) -> 2026 | I131: =MONTH(Table1[[#This Row],[Enrollment_Date]]) -> 1 | J131: =IF(ISNUMBER(D131),D131,"") -> 46036
A132: ENR0131 | B132: Female | C132: Computer Science | D132: 46037 | E132: Full-Time | F132: 0 | G132: Withdrawn | H132: =YEAR(Table1[[#This Row],[Enrollment_Date]]) -> 2026 | I132: =MONTH(Table1[[#This Row],[Enrollment_Date]]) -> 1 | J132: =IF(ISNUMBER(D132),D132,"") -> 46037
A133: ENR0132 | B133: Female | C133: Business Administration | D133: 46038 | E133: Part-Time | F133: 760.13 | G133: Active | H133: =YEAR(Table1[[#This Row],[Enrollment_Date]]) -> 2026 | I133: =MONTH(Table1[[#This Row],[Enrollment_Date]]) -> 1 | J133: =IF(ISNUMBER(D133),D133,"") -> 46038
A134: ENR0133 | B134: Female | C134: Computer Science | D134: 46039 | E134: Full-Time | F134: 958.74 | G134: Active | H134: =YEAR(Table1[[#This Row],[Enrollment_Date]]) -> 2026 | I134: =MONTH(Table1[[#This Row],[Enrollment_Date]]) -> 1 | J134: =IF(ISNUMBER(D134),D134,"") -> 46039
... A160: ENR0159 | B160: Male | C160: non_program | D160: 46065 | E160: non_stady_mode | F160: 738.48 | G160: Active | H160: =YEAR(Table1[[#This Row],[Enrollment_Date]]) -> 2026 | I160: =MONTH(Table1[[#This Row],[Enrollment_Date]]) -> 2 | J160: =IF(ISNUMBER(D160),D160,"") -> 46065
A161: ENR0160 | B161: Male | C161: Public Health | D161: non_date | E161: Full-Time | F161: 817.84 | G161: Withdrawn | H161: =YEAR(Table1[[#This Row],[Enrollment_Date]]) -> #VALUE! | I161: =MONTH(Table1[[#This Row],[Enrollment_Date]]) -> #VALUE! | J161: =IF(ISNUMBER(D161),D161,"")
A162: ENR0161 | B162: Female | C162: Data Science | D162: 46092 | E162: Full-Time | F162: 1071.88 | G162: Deferred | H162: =YEAR(Table1[[#This Row],[Enrollment_Date]]) -> 2026 | I162: =MONTH(Table1[[#This Row],[Enrollment_Date]]) -> 3 | J162: =IF(ISNUMBER(D162),D162,"") -> 46092
A163: ENR0162 | B163: Male | C163: Computer Science | D163: 46093 | E163: Part-Time | F163: 1021.08 | G163: Withdrawn | H163: =YEAR(Table1[[#This Row],[Enrollment_Date]]) -> 2026 | I163: =MONTH(Table1[[#This Row],[Enrollment_Date]]) -> 3 | J163: =IF(ISNUMBER(D163),D163,"") -> 46093
A164: ENR0163 | B164: Female | C164: Business Administration | D164: 46094 | E164: Online | F164: 761.3 | G164: Withdrawn | H164: =YEAR(Table1[[#This Row],[Enrollment_Date]]) -> 2026 | I164: =MONTH(Table1[[#This Row],[Enrollment_Date]]) -> 3 | J164: =IF(ISNUMBER(D164),D164,"") -> 46094
A165: ENR0164 | B165: Female | C165: Data Science | D165: 46095 | E165: Full-Time | F165: 1020.21 | G165: Active | H165: =YEAR(Table1[[#This Row],[Enrollment_Date]]) -> 2026 | I165: =MONTH(Table1[[#This Row],[Enrollment_Date]]) -> 3 | J165: =IF(ISNUMBER(D165),D165,"") -> 46095
A166: ENR0165 | B166: Male | C166: Public Health | D166: 46096 | E166: Online | F166: 886.5 | G166: Active | H166: =YEAR(Table1[[#This Row],[Enrollment_Date]]) -> 2026 | I166: =MONTH(Table1[[#This Row],[Enrollment_Date]]) -> 3 | J166: =IF(ISNUMBER(D166),D166,"") -> 46096
A167: ENR0166 | B167: Female | C167: Data Science | D167: 46097 | E167: Part-Time | F167: 1019.28 | G167: Active | H167: =YEAR(Table1[[#This Row],[Enrollment_Date]]) -> 2026 | I167: =MONTH(Table1[[#This Row],[Enrollment_Date]]) -> 3 | J167: =IF(ISNUMBER(D167),D167,"") -> 46097
A168: ENR0167 | B168: Male | C168: Computer Science | D168: non_date | E168: Full-Time | F168: 1057.91 | G168: Active | H168: =YEAR(Table1[[#This Row],[Enrollment_Date]]) -> #VALUE! | I168: =MONTH(Table1[[#This Row],[Enrollment_Date]]) -> #VALUE! | J168: =IF(ISNUMBER(D168),D168,"")
...

Sheet Enrollment_Row
A1: Student_ID | B1: Gender | C1: Program | D1: Enrollment_Date | E1: Study_Mode | F1: Tuition_Fee | G1: Enrollment_Status
A2: ENR0001 | B2: Male | C2: Computer Science | D2: 45994 | E2: Full-Time | F2: 927.99
A3: ENR0002 | B3: Female | C3: Computer Science | D3: 45772 | E3: Online | F3: 929.8 | G3: Active
A4: ENR0003 | B4: Male | C4: Public Health | D4: 46105 | E4: Full-Time | F4: 1028.35 | G4: Active
A5: ENR0004 | B5: Male | C5: Data Science | D5: 46121 | E5: Part-Time | G5: Active
A6: ENR0005 | B6: Female | C6: Computer Science | D6: 46010 | E6: full-time | F6: 1035.39 | G6: Active
A7: ENR0007 | B7: Female | D7: 45971 | E7: Full-Time | F7: 1254.82 | G7: Withdrawn
A8: ENR0008 | B8: Male | C8: Public Health | D8: 46040 | E8: Full-Time | F8: 825.79 | G8: Graduated
A9: ENR0009 | B9: Male | C9: Computer Science | D9: 45726 | E9: Part-Time | F9: 1034.99 | G9: Deferred
A10: ENR0010 | B10: Female | C10: Computer Science | D10: 45843 | E10: Full-Time | F10: 1006.87 | G10: Active | I10: =SUMIF(B2:B301,"Female",F2:F301) -> 137600.67
A11: ENR0011 | C11: Computer Science | D11: 45730 | E11: Part-Time | F11: 896.69 | G11: Graduated
A12: ENR0012 | B12: Female | C12: Computer Science | D12: 45692 | E12: Part-Time | F12: 1046.24 | G12: Graduated
A13: ENR0014 | B13: Male | C13: Data Science | D13: 46010 | F13: - | G13: Active
A14: ENR0015 | B14: Female | C14: Data Science | D14: 46221 | E14: Full-Time | F14: 1140.65 | G14: Active
A15: ENR0016 | B15: Male | C15: Computer Science | D15: 46011 | E15: Full-Time | F15: 890.93 | G15: Active
A16: ENR0017 | B16: Male | D16: 45748 | E16: Full-Time | F16: 1239.34 | G16: Withdrawn
A17: ENR0018 | B17: Female | D17: 46025 | E17: Online | F17: 1245.26 | G17: Deferred
A18: ENR0019 | B18: Male | C18: Data Science | D18: 46031 | E18: Full-Time | F18: 1175.69 | G18: Graduated
A19: ENR0020 | B19: Female | C19: Computer Science | D19: 46087 | E19: Online | F19: 905.83 | G19: Graduated
A20: ENR0021 | B20: Male | C20: Economics | D20: 46002 | E20: Part-Time | F20: 893.17 | G20: Active
A21: ENR0022 | C21: Data Science | D21: 45912 | E21: Full-Time | F21: 1065.37 | G21: Active
A22: ENR0023 | B22: Female | C22: Data Science | D22: 45801 | E22: Full-Time | F22: 1172 | G22: Deferred
A23: ENR0024 | B23: Female | C23: Public Health | D23: 45942 | E23: Full-Time | G23: Withdrawn
A24: ENR0025 | B24: Female | C24: Data Science | E24: Full-Time | F24: 1129.42 | G24: Graduated
A25: ENR0026 | B25: Female | C25: Data Science | D25: NULL | E25: Full-Time | F25: 1048 | G25: Active
A26: ENR0026 | B26: Female | C26: Data Science | D26: 45887 | E26: Full-Time | G26: Active
A27: ENR0027 | B27: Male | C27: Computer Science | D27: 45928 | F27: 1014.33 | G27: Graduated
A28: ENR0028 | B28: Male | C28: Public Health | D28: 45855 | E28: Full-Time | F28: 877.02 | G28: Active
A29: ENR0029 | B29: Female | C29: Data Science | D29: 45668 | E29: Full-Time | G29: Active
A30: ENR0030 | B30: Male | C30: Public Health | D30: 45669 | E30: Full-Time | F30: 922.81 | G30: Active
A31: ENR0031 | B31: Male | C31: Data Science | D31: 45706 | E31: Full-Time | F31: 1155.26 | G31: Graduated
A32: ENR0032 | B32: Female | C32: Computer Science | D32: 45968 | E32: Full-Time | F32: 1064.99 | G32: Active
A33: ENR0033 | B33: Female | C33: Business Administration | F33: 808.66 | G33: Active
A34: ENR0034 | B34: Female | C34: Business Administration | D34: 46066 | E34: Part-Time | F34: 834.99 | G34: Active
A35: ENR0035 | B35: Male | C35: Public Health | D35: 45804 | E35: Full-Time | F35: 972.65
A36: ENR0036 | B36: Male | C36: Computer Science | D36: 45892 | E36: Online | F36: 886.2
A37: ENR0037 | B37: Female | C37: Business Administration | D37: 45993 | F37: 866.74 | G37: N/A
A38: ENR0038 | B38: Male | C38: Data Science | D38: 45738 | E38: Full-Time | G38: Active
A39: ENR0039 | B39: Female | C39: Business Administration | D39: 45983 | E39: Online | F39: 750.89 | G39: Active
A40: ENR0040 | B40: Male | C40: Business Administration | D40: 45727 | E40: Full-Time | F40: 736.59 | G40: Active
A41: ENR0041 | B41: Female | C41: Computer Science | D41: 46007 | E41: Full-Time | F41: 1071.49 | G41: Graduated
A42: ENR0042 | B42: Male | C42: Business Administration | E42: Part-Time | F42: 838.79 | G42: Active
A43: ENR0043 | C43: Public Health | D43: 46213 | E43: Online | F43: 960.91 | G43: Active
A44: ENR0044 | B44: Male | C44: Engineering | D44: 46209 | E44: Part-Time | F44: 1354.04 | G44: Deferred
A45: ENR0045 | B45: Male | C45: Business Administration | D45: 45917 | E45: Full-Time | F45: 789.47 | G45: Deferred
A46: ENR0046 | B46: Female | C46: Engineering | D46: 45778 | E46: Online | F46: 1208.64
A47: ENR0047 | B47: Female | C47: Business Administration | D47: 46139 | E47: Full-Time | F47: 792.99 | G47: Active
A48: ENR0048 | B48: Female | C48: Data Science | D48: 45908 | E48: Online | F48: 1084.15 | G48: Graduated
A49: ENR0049 | B49: Female | C49: Engineering | D49: 46121 | E49: Full-Time | F49: 1305.94 | G49: Graduated
A50: ENR0050 | B50: Female | C50: Public Health | D50: 46144 | E50: Full-Time | G50: Graduated
A51: ENR0051 | B51: Male | C51: Public Health | E51: Part-Time | F51: 1000.77 | G51: Active
A52: ENR0052 | B52: Male | C52: Computer Science | D52: 45983 | E52: Full-Time | F52: 928.88 | G52: Active
A53: ENR0052 | B53: Male | C53: Computer Science | D53: 45983 | E53: Full-Time | F53: 928.88 | G53: Active
A54: ENR0053 | B54: Female | C54: Data Science | D54: 45903 | E54: Full-Time | G54: Graduated
A55: ENR0054 | B55: Male | C55: Engineering | D55: 45685 | E55: Full-Time | F55: 1142.6 | G55: Active
A56: ENR0056 | B56: Male | C56: Computer Science | D56: 46052 | E56: Full-Time | F56: 1042.66 | G56: Graduated
A57: ENR0057 | B57: Male | C57: Data Science | D57: 46143 | E57: Full-Time | F57: 1252.22 | G57: Deferred
A58: ENR0058 | B58: Male | C58: Engineering | E58: Full-Time | F58: 1116.57 | G58: Active
A59: ENR0059 | B59: Female | C59: Engineering | D59: 45817 | E59: Part-Time | F59: 1120 | G59: Active
A60: ENR0060 | B60: Male | C60: Data Science | D60: 46009 | E60: Full-Time | F60: 1187.61 | G60: Active
A61: ENR0061 | B61: Female | C61: Economics | D61: 45911 | E61: Part-Time | F61: 874.8 | G61: Active
A62: ENR0061 | B62: Female | C62: Economics | D62: 45911 | E62: Part-Time | F62: 874.8 | G62: Active
A63: ENR0062 | B63: Female | C63: Public Health | D63: 45928 | E63: Full-Time | F63: 816.32 | G63: Graduated
A64: ENR0063 | B64: Female | C64: Public Health | D64: 45945 | E64: Full-Time | F64: 944.77 | G64: Graduated
A65: ENR0065 | B65: Male | C65: Engineering | D65: 45774 | F65: 1155.73 | G65: Active
A66: ENR0066 | B66: Female | C66: Computer Science | D66: 45682 | E66: Online | F66: 1014.93 | G66: Graduated
A67: ENR0067 | B67: Female | C67: Data Science | D67: 45918 | E67: Full-Time | F67: 1186.5 | G67: Deferred
A68: ENR0068 | B68: Male | C68: Business Administration | D68: 46162 | E68: Full-Time | F68: 887.69 | G68: Withdrawn
A69: ENR0069 | B69: Female | C69: Engineering | D69: 46127 | E69: Full-Time | F69: 1164.86 | G69: Withdrawn
A70: ENR0070 | C70: Business Administration | D70: 45881 | E70: Part-Time | F70: 865.04 | G70: Active
A71: ENR0071 | B71: Female | C71: Economics | D71: 45878 | E71: Full-Time | F71: 794.13 | G71: Active
A72: ENR0071 | B72: Female | C72: Economics | D72: 45878 | E72: Full-Time | F72: 794.13 | G72: Active
A73: ENR0072 | B73: Female | C73: Engineering | D73: 46102 | E73: Online | G73: Active
A74: ENR0073 | B74: Male | C74: Data Science | D74: 46113 | E74: Full-Time | F74: 1046.94 | G74: Graduated
A75: ENR0074 | B75: Male | C75: Data Science | D75: 46196 | E75: Part-Time | F75: 1111.25 | G75: Graduated
A76: ENR0075 | B76: MALE | D76: 45896 | E76: Part-Time | F76: 833.87 | G76: Active
A77: ENR0076 | B77: Female | C77: Data Science | D77: 45952 | E77: Online | F77: 1244.64 | G77: Graduated
A78: ENR0077 | B78: Female | C78: Computer Science | D78: 45842 | E78: Full-Time | F78: 1080.26 | G78: Active
A79: ENR0079 | B79: Male | C79: Economics | D79: 45898 | E79: Full-Time | F79: 866.01 | G79: Active
A80: ENR0080 | B80: Female | C80: Computer Science | D80: 46184 | E80: Part-Time | F80: 1083.36 | G80: Active
A81: ENR0081 | B81: Male | C81: Computer Science | D81: 45869 | E81: Part-Time | F81: 1083.15 | G81: Active
A82: ENR0082 | B82: Male | C82: Data Science | D82: 45706 | E82: Full-Time | F82: 1259.54 | G82: Deferred
A83: ENR0083 | B83: Female | C83: Engineering | D83: 45987 | E83: Full-Time | F83: 1145.76 | G83: Active
A84: ENR0084 | B84: Male | C84: Economics | D84: 46075 | E84: Full-Time | F84: 804.04 | G84: Active
A85: ENR0085 | B85: Male | C85: Data Science | D85: 46039 | F85: 1146.34 | G85: Active
A86: ENR0086 | B86: Female | C86: Data Science | D86: 46212 | E86: Part-Time | F86: 1197.4 | G86: Active
A87: ENR0087 | B87: Female | C87: Data Science | D87: 46040 | E87: Part-Time | F87: 1098.38 | G87: Active
A88: ENR0088 | B88: Male | C88: Business Administration | D88: 45854 | E88: Online | F88: 720.2
A89: ENR0089 | B89: Female | C89: Engineering | D89: 46212 | E89: Full-Time | F89: 1156.29 | G89: Deferred
A90: ENR0090 | B90: Male | C90: Engineering | D90: 45811 | E90: Full-Time | F90: 1138.77 | G90: Active
A91: ENR0091 | B91: Male | C91: Engineering | D91: 45933 | E91: Online | F91: 1358.18
A92: ENR0092 | B92: Female | C92: Data Science | D92: 45787 | E92: Full-Time | F92: 1103.72 | G92: Deferred
A93: ENR0093 | B93: Male | C93: Public Health | D93: 46199 | E93: Full-Time | F93: 968.97 | G93: Active
A94: ENR0094 | B94: Male | C94: Engineering | D94: 46016 | E94: Full-Time | F94: 1352.42 | G94: Deferred
A95: ENR0095 | B95: Female | C95: Computer Science | D95: 45675 | E95: Online | F95: 1014.23 | G95: Active
A96: ENR0096 | B96: Male | C96: Computer Science | D96: 45774 | E96: Online | F96: 997.33 | G96: Active
A97: ENR0097 | B97: Female | C97: Data Science | D97: 46115 | E97: Part-Time | F97: 990.07
A98: ENR0098 | B98: Male | C98: Business Administration | D98: 46041 | E98: Online | F98: 898.83 | G98: Active
A99: ENR0099 | B99: Male | C99: Economics | D99: 46162 | E99: Full-Time | F99: 851.3 | G99: Active
A100: ENR0100 | B100: Female | C100: Business Administration | D100: 46209 | E100: Full-Time | F100: 877.02 | G100: Graduated
...

Sheet Analaysi_data
A1: DATA BLANKES | G1: DATA COLOUM AND ROW
A3: 1 | B3: Student_ID | C3: =COUNTBLANK(Enrollment_Row!A2:A301) -> 15 | H3: DATA | I3: ROW | J3: BLANK
A4: 2 | B4: Gender | C4: =COUNTBLANK(Enrollment_Row!B2:B301) -> 15 | H4: Student_ID | I4: 301 | J4: 15 | K4: =I4-J4 -> 286
A5: 3 | B5: Program | C5: =COUNTBLANK(Enrollment_Row!C2:C301) -> 15 | H5: Gender | I5: 301 | J5: 15 | K5: =I5-J5 -> 286
A6: 4 | B6: Enrollment_Date | C6: =COUNTBLANK(Enrollment_Row!D2:D301) -> 16 | H6: Program | I6: 301 | J6: 15 | K6: =I6-J6 -> 286
A7: 5 | B7: Study_Mode | C7: =COUNTBLANK(Enrollment_Row!E2:E301) -> 15 | H7: Enrollment_Date | I7: 301 | J7: 16 | K7: =I7-J7 -> 285
A8: 6 | B8: Tuition_Fee | C8: =COUNTBLANK(Enrollment_Row!F2:F301) -> 15 | H8: Study_Mode | I8: 301 | J8: 15 | K8: =I8-J8 -> 286
A9: 7 | B9: Enrollment_Status | C9: =COUNTBLANK(Enrollment_Row!G2:G301) -> 16 | H9: Tuition_Fee | I9: 301 | J9: 15 | K9: =I9-J9 -> 286
A10: TOTAL BLANK | C10: =SUM(C3:C9) -> 107 | H10: Enrollment_Status | I10: 301 | J10: 16 | K10: =I10-J10 -> 285
H11: TOTAL DATA | K11: =SUM(K4:K10) -> 2000
A23: GENDER | G23: PROGRAM | L23: STUDY MODE | Q23: ENROLLMENT_STATUS
A24: 1 | B24: Male | C24: =COUNTIF(Enrollment_Row!B2:B301,"Female") -> 148 | G24: 1 | H24: BA | I24: =COUNTIF(Enrollment_Row!C2:C301,"BA") -> 1 | L24: 1 | M24: Full-Time | N24: =COUNTIF(Enrollment_Row!E2:E301,"Full-Time") -> 162 | Q24: 1 | R24: Active | S24: =COUNTIF(Enrollment_Row!G2:G301,"Active") -> 175
A25: 2 | B25: Female | C25: =COUNTIF(Enrollment_Row!B2:B301,"Male") -> 136 | G25: 2 | H25: Business Administration | I25: =COUNTIF(Enrollment_Row!C2:C301,"Business Administration") -> 46 | L25: 2 | M25: Part-Time | N25: =COUNTIF(Enrollment_Row!E2:E301,"Part-Time") -> 59 | Q25: 2 | R25: Deferred | S25: =COUNTIF(Enrollment_Row!G2:G301,"Deferred") -> 27
A26: 3 | B26: blank | C26: =COUNTIF(Enrollment_Row!B2:B301,"") -> 15 | G26: 3 | H26: Computer Science | I26: =COUNTIF(Enrollment_Row!C2:C301,"Computer Science") -> 73 | L26: 3 | M26: Online | N26: =COUNTIF(Enrollment_Row!E2:E301,"Online") -> 60 | Q26: 3 | R26: Graduated | S26: =COUNTIF(Enrollment_Row!G2:G301,"Graduated") -> 64
A27: 4 | B27: non value | C27: =COUNTIF(Enrollment_Row!B2:B301,"-") -> 1 | G27: 4 | H27: CS | I27: =COUNTIF(Enrollment_Row!C2:C301,"CS") -> 1 | L27: 4 | M27: N/A | N27: =COUNTIF(Enrollment_Row!E2:E301,"N/A") -> 2 | Q27: 4 | R27: N/A | S27: =COUNTIF(Enrollment_Row!G2:G301,"N/A") -> 2
A28: 5 | G28: 5 | H28: Data Science | I28: =COUNTIF(Enrollment_Row!C2:C301,"Data Science") -> 65 | L28: 5 | M28: NULL | N28: =COUNTIF(Enrollment_Row!E2:E301,"NULL") -> 2 | Q28: 5 | R28: Withdrawn | S28: =COUNTIF(Enrollment_Row!G2:G301,"Withdrawn") -> 16
A29: TOTAL | C29: =SUM(C24:C28) -> 300 | G29: 6 | H29: Economics | I29: =COUNTIF(Enrollment_Row!C2:C301,"Economics") -> 25 | L29: 6 | M29: Blank | N29: =COUNTIF(Enrollment_Row!E2:E301,"") -> 15 | Q29: 6 | R29: Blanks | S29: =COUNTIF(Enrollment_Row!G2:G301,"") -> 16
G30: 7 | H30: Engineering | I30: =COUNTIF(Enrollment_Row!C2:C301,"Engineering") -> 37 | L30: TOTAL | N30: =SUM(N24:N29) -> 300 | Q30: TOTAL | S30: =SUM(S24:S29) -> 300
G31: 8 | H31: Public Health | I31: =COUNTIF(Enrollment_Row!C2:C301,"Public Health") -> 35
G32: 9 | H32: NULL | I32: =COUNTIF(Enrollment_Row!C2:C301,"NULL") -> 1
G33: 10 | H33: Unknown | I33: =COUNTIF(Enrollment_Row!C2:C301,"Unknown") -> 1
G34: 11 | H34: blank | I34: =COUNTIF(Enrollment_Row!C2:C301,"") -> 15
G35: TOTAL | I35: =SUM(I24:I34) -> 300
A36: GENDER BY Tuition_Fee
A37: 1 | B37: Male | C37: =SUMIF(Enrollment_Row!B2:B301,"Male",Enrollment_Row!F2:F301) -> 127920.58
A38: 2 | B38: Female | C38: =SUMIF(Enrollment_Row!B2:B301,"Female",Enrollment_Row!F2:F301) -> 137600.67
A39: 3 | B39: blank | C39: =SUMIF(Enrollment_Row!B2:B301,"",Enrollment_Row!F2:F301) -> 14380
A40: 4 | B40: non value | C40: =SUMIF(Enrollment_Row!B2:B301,"-",Enrollment_Row!F2:F301) -> 1021.44
A41: TOTAL | C41: =SUM(C37:C40) -> 280922.69
A46: Program Tuition | G46: Erollment_status By Tuition | L46: Student_ID Dublicate | R46: Student_ID Apsent | W46: error text
B47: Program | C47: Tuition | H47: Erollment | I47: Tuition | R47: 1 | S47: 6 | X47: full-time | Y47: 1 | Z47: Full-Time
A48: 1 | B48: BA | C48: =SUMIF(Enrollment_Row!C2:C301,"BA",Enrollment_Row!F2:F301) -> 799.37 | H48: Active | I48: =SUMIF(Enrollment_Row!G2:G301,"Active",Enrollment_Row!F2:F301) -> 160575.33 | L48: 1 | M48: 26 | N48: 2 | R48: 2 | S48: 13 | X48: part-time | Y48: 1 | Z48: Part-Time
A49: 2 | B49: Business Administration | C49: =SUMIF(Enrollment_Row!C2:C301,"Business Administration",Enrollment_Row!F2:F301) -> 35818.13 | H49: Deferred | I49: =SUMIF(Enrollment_Row!G2:G301,"Deferred",Enrollment_Row!F2:F301) -> 26444.95 | L49: 2 | M49: 52 | N49: 2 | R49: 3 | S49: 55 | X49: FULL-TIME | Y49: 1 | Z49: Full-Time
A50: 3 | B50: Computer Science | C50: =SUMIF(Enrollment_Row!C2:C301,"Computer Science",Enrollment_Row!F2:F301) -> 67508.92 | H50: Graduated | I50: =SUMIF(Enrollment_Row!G2:G301,"Graduated",Enrollment_Row!F2:F301) -> 61321.28 | L50: 3 | M50: 61 | N50: 2 | R50: 4 | S50: 64 | X50: PART-TIME | Y50: 1 | Z50: Part-Time
A51: 4 | B51: CS | C51: =SUMIF(Enrollment_Row!C2:C301,"CS",Enrollment_Row!F2:F301) -> 1018 | H51: N/A | I51: =SUMIF(Enrollment_Row!G2:G301,"N/A",Enrollment_Row!F2:F301) -> 1767.91 | L51: 4 | M51: 71 | N51: 2 | R51: 5 | S51: 78 | X51: BA | Y51: 1 | Z51: Business Administration
A52: 5 | B52: Data Science | C52: =SUMIF(Enrollment_Row!C2:C301,"Data Science",Enrollment_Row!F2:F301) -> 65662.73 | H52: Withdrawn | I52: =SUMIF(Enrollment_Row!G2:G301,"Withdrawn",Enrollment_Row!F2:F301) -> 14526.77 | L52: 5 | M52: 199 | N52: 2 | R52: 6 | S52: 146 | X52: CS | Y52: 1 | Z52: Computer Science
A53: 6 | B53: Economics | C53: =SUMIF(Enrollment_Row!C2:C301,"Economics",Enrollment_Row!F2:F301) -> 19402.25 | H53: Blanks | I53: =SUMIF(Enrollment_Row!G2:G301,"",Enrollment_Row!F2:F301) -> 16286.45 | L53: 6 | M53: 256 | N53: 2 | R53: 7 | S53: 161 | X53: ACTIVE | Y53: 1 | Z53: Active
A54: 7 | B54: Engineering | C54: =SUMIF(Enrollment_Row!C2:C301,"Engineering",Enrollment_Row!F2:F301) -> 42936.93 | G54: TOTAL | I54: =SUM(I48:I53) -> 280922.69 | L54: 7 | M54: 279 | N54: 2 | R54: 8 | S54: 168 | X54: deferred | Y54: 1 | Z54: Deferred
A55: 8 | B55: Public Health | C55: =SUMIF(Enrollment_Row!C2:C301,"Public Health",Enrollment_Row!F2:F301) -> 30457.95 | R55: 9 | S55: 198 | X55: graduated | Y55: 1 | Z55: Graduated
A56: 9 | B56: NULL | C56: =SUMIF(Enrollment_Row!C2:C301,"NULL",Enrollment_Row!F2:F301) -> 936.29 | R56: 10 | S56: 236
A57: 10 | B57: Unknown | C57: =SUMIF(Enrollment_Row!C2:C301,"Unknown",Enrollment_Row!F2:F301) -> 738.48 | R57: 11 | S57: 269
A58: 11 | B58: blank | C58: =SUMIF(Enrollment_Row!C2:C301,"",Enrollment_Row!F2:F301) -> 15643.64 | R58: 12 | S58: 277
A59: TOTAL | C59: =SUM(C48:C58) -> 280922.69 | R59: 13 | S59: 283
A65: Study_Mode By Tuition
B66: study_mode | C66: Tuition
B67: Full-Time | C67: =SUMIF(Enrollment_Row!E2:E301,"Full-Time",Enrollment_Row!F2:F301) -> 154294.34
B68: Part-Time | C68: =SUMIF(Enrollment_Row!E2:E301,"Part-Time",Enrollment_Row!F2:F301) -> 56114.07
B69: Online | C69: =SUMIF(Enrollment_Row!E2:E301,"Online",Enrollment_Row!F2:F301) -> 52538.5
B70: N/A | C70: =SUMIF(Enrollment_Row!E2:E301,"N/A",Enrollment_Row!F2:F301) -> 2105.08
B71: NULL | C71: =SUMIF(Enrollment_Row!E2:E301,"NULL",Enrollment_Row!F2:F301) -> 1660.29
B72: Blank | C72: =SUMIF(Enrollment_Row!E2:E301,"",Enrollment_Row!F2:F301) -> 14210.41
A73: TOTAL | C73: =SUM(C67:C72) -> 280922.69
